kmr1_shorten/__init__.py
kmr1_shorten/shorten.py
kmr1_shorten-1.0.4.dist-info/licenses/LICENSE
kmr1_shorten-1.0.4.dist-info/METADATA
kmr1_shorten-1.0.4.dist-info/WHEEL
kmr1_shorten-1.0.4.dist-info/entry_points.txt
kmr1_shorten-1.0.4.dist-info/top_level.txt
kmr1_shorten-1.0.4.dist-info/RECORD
