Metadata-Version: 2.4
Name: kmr1-shorten
Version: 1.0.4
Summary: Kmr¹ APIを使用してURLを短縮するコマンドラインツール
Author: Lapius7bot Technology Co.
Author-email: contact-us@lapius7.com
License: MIT
Project-URL: Source, https://github.com/Lapius7/pip.kmr1-shorten
Project-URL: Bug Tracker, https://github.com/Lapius7/pip.kmr1-shorten/issues
License-File: LICENSE
Dynamic: author
Dynamic: author-email
Dynamic: description
Dynamic: description-content-type
Dynamic: license
Dynamic: license-file
Dynamic: project-url
Dynamic: summary
